takumi_ext/__init__.py
takumi_ext-0.1.2.dist-info/top_level.txt
takumi_ext-0.1.2.dist-info/METADATA
takumi_ext-0.1.2.dist-info/DESCRIPTION.rst
takumi_ext-0.1.2.dist-info/metadata.json
takumi_ext-0.1.2.dist-info/WHEEL
takumi_ext-0.1.2.dist-info/RECORD
