Metadata-Version: 2.0
Name: takumi-ext
Version: 0.1.2
Summary: Simple extension system for extending Takumi framework
Home-page: https://github.com/elemepi/takumi-ext
Author: Eleme Lab
Author-email: imaralla@icloud.com
License: UNKNOWN
Platform: UNKNOWN
Requires-Dist: takumi-config
